l6e_forge/__init__.py
l6e_forge/config_managers/__init__.py
l6e_forge/config_managers/base.py
l6e_forge/config_managers/toml.py
l6e_forge/core/__init__.py
l6e_forge/core/agents/__init__.py
l6e_forge/core/agents/base.py
l6e_forge/dev/__init__.py
l6e_forge/dev/handler.py
l6e_forge/dev/reloader.py
l6e_forge/dev/service.py
l6e_forge/events/bus/__init__.py
l6e_forge/events/bus/base.py
l6e_forge/events/handlers/__init__.py
l6e_forge/events/handlers/base.py
l6e_forge/infra/compose.py
l6e_forge/logger/__init__.py
l6e_forge/logger/base.py
l6e_forge/logging/__init__.py
l6e_forge/logging/base.py
l6e_forge/logging/get_logger.py
l6e_forge/logging/print_logger.py
l6e_forge/memory/backends/__init__.py
l6e_forge/memory/backends/base.py
l6e_forge/memory/backends/inmemory.py
l6e_forge/memory/backends/qdrant.py
l6e_forge/memory/collections.py
l6e_forge/memory/conversation/base.py
l6e_forge/memory/conversation/postgres.py
l6e_forge/memory/conversation/provider.py
l6e_forge/memory/embeddings/base.py
l6e_forge/memory/embeddings/lmstudio.py
l6e_forge/memory/embeddings/mock.py
l6e_forge/memory/embeddings/ollama.py
l6e_forge/memory/managers/__init__.py
l6e_forge/memory/managers/base.py
l6e_forge/memory/managers/memory.py
l6e_forge/models/auto.py
l6e_forge/models/managers/__init__.py
l6e_forge/models/managers/base.py
l6e_forge/models/managers/lmstudio.py
l6e_forge/models/managers/ollama.py
l6e_forge/models/providers/__init__.py
l6e_forge/models/providers/base.py
l6e_forge/models/providers/llamafile.py
l6e_forge/models/providers/openai.py
l6e_forge/models/providers/registry.py
l6e_forge/monitor/__init__.py
l6e_forge/monitor/base.py
l6e_forge/monitor/inmemory.py
l6e_forge/monitor/remote.py
l6e_forge/prompt/__init__.py
l6e_forge/prompt/builder.py
l6e_forge/prompt/loader.py
l6e_forge/runtime/__init__.py
l6e_forge/runtime/base.py
l6e_forge/runtime/container.py
l6e_forge/runtime/local.py
l6e_forge/runtime/monitoring.py
l6e_forge/runtime/result_processing.py
l6e_forge-0.1.0.dist-info/LICENSE
l6e_forge-0.1.0.dist-info/METADATA
l6e_forge-0.1.0.dist-info/WHEEL
l6e_forge-0.1.0.dist-info/RECORD
