Metadata-Version: 2.3
Name: l6e-forge
Version: 0.1.0
Summary: Build & Deploy local agents with ease - alpha
License: Apache 2.0
Author: l6e AI
Author-email: hello@l6e.ai
Requires-Python: >=3.13,<4.0
Classifier: License :: Other/Proprietary License
Classifier: Programming Language :: Python :: 3
Classifier: Programming Language :: Python :: 3.13
Project-URL: Docs, https://docs.l6e.ai
Project-URL: Homepage, https://l6e.ai
Project-URL: Issues, https://github.com/l6e-ai/forge/issues
